{"order_id": "ORD001", "customer_id": "CUST001", "order_date": "2024-01-15", "total_amount": 299.99, "status": "completed", "shipping_address": "123 Main St, New York, NY 10001", "payment_method": "credit_card", "created_ts": "2024-01-15 10:30:00"}
{"order_id": "ORD002", "customer_id": "CUST002", "order_date": "2024-01-15", "total_amount": 149.50, "status": "processing", "shipping_address": "456 Oak Ave, Los Angeles, CA 90210", "payment_method": "paypal", "created_ts": "2024-01-15 10:31:00"}
{"order_id": "ORD003", "customer_id": "CUST003", "order_date": "2024-01-15", "total_amount": 89.99, "status": "shipped", "shipping_address": "789 Pine Rd, Chicago, IL 60601", "payment_method": "credit_card", "created_ts": "2024-01-15 10:32:00"}
{"order_id": "ORD004", "customer_id": "CUST004", "order_date": "2024-01-15", "total_amount": 199.99, "status": "completed", "shipping_address": "321 Elm St, Houston, TX 77001", "payment_method": "debit_card", "created_ts": "2024-01-15 10:33:00"}
{"order_id": "ORD005", "customer_id": "CUST005", "order_date": "2024-01-15", "total_amount": 79.99, "status": "processing", "shipping_address": "654 Maple Dr, Phoenix, AZ 85001", "payment_method": "credit_card", "created_ts": "2024-01-15 10:34:00"}
{"order_id": "ORD006", "customer_id": "CUST006", "order_date": "2024-01-15", "total_amount": 399.99, "status": "completed", "shipping_address": "987 Cedar Ln, Philadelphia, PA 19101", "payment_method": "credit_card", "created_ts": "2024-01-15 10:35:00"}
{"order_id": "ORD007", "customer_id": "CUST007", "order_date": "2024-01-15", "total_amount": 129.99, "status": "shipped", "shipping_address": "147 Birch Way, San Antonio, TX 78201", "payment_method": "paypal", "created_ts": "2024-01-15 10:36:00"}
{"order_id": "ORD008", "customer_id": "CUST008", "order_date": "2024-01-15", "total_amount": 249.99, "status": "processing", "shipping_address": "258 Spruce Ct, San Diego, CA 92101", "payment_method": "credit_card", "created_ts": "2024-01-15 10:37:00"}
{"order_id": "ORD009", "customer_id": "CUST009", "order_date": "2024-01-15", "total_amount": 179.99, "status": "completed", "shipping_address": "369 Willow St, Dallas, TX 75201", "payment_method": "debit_card", "created_ts": "2024-01-15 10:38:00"}
{"order_id": "ORD010", "customer_id": "CUST010", "order_date": "2024-01-15", "total_amount": 159.99, "status": "shipped", "shipping_address": "741 Aspen Ave, San Jose, CA 95101", "payment_method": "credit_card", "created_ts": "2024-01-15 10:39:00"}
